<annotation><folder /><filename>C:\Users\rober_abgp8xd\Desktop\canada-trabajo\RICO_CLAY_data\unique_uis.tar\unique_uis\combined\27202.jpg</filename>
<path>C:\Users\rober_abgp8xd\Desktop\canada-trabajo\RICO_CLAY_data\unique_uis.tar\unique_uis\combined\27202.jpg</path>
<source><database>RICO</database></source><size><width>360</width><height>640</height><depth>3</depth></size><segmented>0</segmented><object>
    <difficult>0</difficult>
    <bndbox>
        <xmin>0</xmin>
        <ymin>30</ymin>
        <xmax>360</xmax>
        <ymax>62</ymax>
    </bndbox>
    <name>CONTAINER</name>
</object>
<object>
    <difficult>0</difficult>
    <bndbox>
        <xmin>95</xmin>
        <ymin>30</ymin>
        <xmax>209</xmax>
        <ymax>53</ymax>
    </bndbox>
    <name>TEXT</name>
</object>
<object>
    <difficult>0</difficult>
    <bndbox>
        <xmin>218</xmin>
        <ymin>30</ymin>
        <xmax>264</xmax>
        <ymax>53</ymax>
    </bndbox>
    <name>TEXT</name>
</object>
<object>
    <difficult>0</difficult>
    <bndbox>
        <xmin>0</xmin>
        <ymin>62</ymin>
        <xmax>360</xmax>
        <ymax>508</ymax>
    </bndbox>
    <name>IMAGE</name>
</object>
<object>
    <difficult>0</difficult>
    <bndbox>
        <xmin>36</xmin>
        <ymin>508</ymin>
        <xmax>176</xmax>
        <ymax>550</ymax>
    </bndbox>
    <name>PICTOGRAM</name>
</object>
</annotation>