<annotation><folder /><filename>C:\Users\rober_abgp8xd\Desktop\canada-trabajo\RICO_CLAY_data\unique_uis.tar\unique_uis\combined\23729.jpg</filename>
<path>C:\Users\rober_abgp8xd\Desktop\canada-trabajo\RICO_CLAY_data\unique_uis.tar\unique_uis\combined\23729.jpg</path>
<source><database>RICO</database></source><size><width>360</width><height>640</height><depth>3</depth></size><segmented>0</segmented><object>
    <difficult>0</difficult>
    <bndbox>
        <xmin>0</xmin>
        <ymin>0</ymin>
        <xmax>1440</xmax>
        <ymax>2234</ymax>
    </bndbox>
    <name>CONTAINER</name>
</object>
<object>
    <difficult>0</difficult>
    <bndbox>
        <xmin>200</xmin>
        <ymin>90</ymin>
        <xmax>1240</xmax>
        <ymax>468</ymax>
    </bndbox>
    <name>IMAGE</name>
</object>
<object>
    <difficult>0</difficult>
    <bndbox>
        <xmin>275</xmin>
        <ymin>340</ymin>
        <xmax>1164</xmax>
        <ymax>468</ymax>
    </bndbox>
    <name>TEXT</name>
</object>
<object>
    <difficult>0</difficult>
    <bndbox>
        <xmin>222</xmin>
        <ymin>626</ymin>
        <xmax>704</xmax>
        <ymax>833</ymax>
    </bndbox>
    <name>CONTAINER</name>
</object>
<object>
    <difficult>0</difficult>
    <bndbox>
        <xmin>268</xmin>
        <ymin>633</ymin>
        <xmax>657</xmax>
        <ymax>825</ymax>
    </bndbox>
    <name>CONTAINER</name>
</object>
<object>
    <difficult>0</difficult>
    <bndbox>
        <xmin>268</xmin>
        <ymin>633</ymin>
        <xmax>549</xmax>
        <ymax>825</ymax>
    </bndbox>
    <name>TEXT</name>
</object>
<object>
    <difficult>0</difficult>
    <bndbox>
        <xmin>558</xmin>
        <ymin>704</ymin>
        <xmax>657</xmax>
        <ymax>825</ymax>
    </bndbox>
    <name>TEXT</name>
</object>
<object>
    <difficult>0</difficult>
    <bndbox>
        <xmin>739</xmin>
        <ymin>626</ymin>
        <xmax>1221</xmax>
        <ymax>833</ymax>
    </bndbox>
    <name>CONTAINER</name>
</object>
<object>
    <difficult>0</difficult>
    <bndbox>
        <xmin>835</xmin>
        <ymin>633</ymin>
        <xmax>1125</xmax>
        <ymax>825</ymax>
    </bndbox>
    <name>CONTAINER</name>
</object>
<object>
    <difficult>0</difficult>
    <bndbox>
        <xmin>835</xmin>
        <ymin>633</ymin>
        <xmax>1039</xmax>
        <ymax>825</ymax>
    </bndbox>
    <name>TEXT</name>
</object>
<object>
    <difficult>0</difficult>
    <bndbox>
        <xmin>1048</xmin>
        <ymin>704</ymin>
        <xmax>1125</xmax>
        <ymax>825</ymax>
    </bndbox>
    <name>TEXT</name>
</object>
<object>
    <difficult>0</difficult>
    <bndbox>
        <xmin>391</xmin>
        <ymin>527</ymin>
        <xmax>534</xmax>
        <ymax>606</ymax>
    </bndbox>
    <name>TEXT</name>
</object>
<object>
    <difficult>0</difficult>
    <bndbox>
        <xmin>830</xmin>
        <ymin>527</ymin>
        <xmax>1129</xmax>
        <ymax>606</ymax>
    </bndbox>
    <name>TEXT</name>
</object>
<object>
    <difficult>0</difficult>
    <bndbox>
        <xmin>566</xmin>
        <ymin>896</ymin>
        <xmax>873</xmax>
        <ymax>975</ymax>
    </bndbox>
    <name>TEXT</name>
</object>
<object>
    <difficult>0</difficult>
    <bndbox>
        <xmin>218</xmin>
        <ymin>1002</ymin>
        <xmax>718</xmax>
        <ymax>1146</ymax>
    </bndbox>
    <name>BUTTON</name>
</object>
<object>
    <difficult>0</difficult>
    <bndbox>
        <xmin>721</xmin>
        <ymin>1002</ymin>
        <xmax>1221</xmax>
        <ymax>1146</ymax>
    </bndbox>
    <name>BUTTON</name>
</object>
<object>
    <difficult>0</difficult>
    <bndbox>
        <xmin>532</xmin>
        <ymin>1209</ymin>
        <xmax>908</xmax>
        <ymax>1288</ymax>
    </bndbox>
    <name>TEXT</name>
</object>
<object>
    <difficult>0</difficult>
    <bndbox>
        <xmin>221</xmin>
        <ymin>1315</ymin>
        <xmax>721</xmax>
        <ymax>1522</ymax>
    </bndbox>
    <name>CONTAINER</name>
</object>
<object>
    <difficult>0</difficult>
    <bndbox>
        <xmin>329</xmin>
        <ymin>1322</ymin>
        <xmax>612</xmax>
        <ymax>1514</ymax>
    </bndbox>
    <name>TEXT</name>
</object>
<object>
    <difficult>0</difficult>
    <bndbox>
        <xmin>721</xmin>
        <ymin>1315</ymin>
        <xmax>1221</xmax>
        <ymax>1522</ymax>
    </bndbox>
    <name>BUTTON</name>
</object>
<object>
    <difficult>0</difficult>
    <bndbox>
        <xmin>892</xmin>
        <ymin>1379</ymin>
        <xmax>1040</xmax>
        <ymax>1458</ymax>
    </bndbox>
    <name>TEXT</name>
</object>
<object>
    <difficult>0</difficult>
    <bndbox>
        <xmin>643</xmin>
        <ymin>1698</ymin>
        <xmax>796</xmax>
        <ymax>1851</ymax>
    </bndbox>
    <name>IMAGE</name>
</object>
<object>
    <difficult>0</difficult>
    <bndbox>
        <xmin>449</xmin>
        <ymin>1698</ymin>
        <xmax>602</xmax>
        <ymax>1851</ymax>
    </bndbox>
    <name>IMAGE</name>
</object>
<object>
    <difficult>0</difficult>
    <bndbox>
        <xmin>255</xmin>
        <ymin>1698</ymin>
        <xmax>408</xmax>
        <ymax>1851</ymax>
    </bndbox>
    <name>IMAGE</name>
</object>
<object>
    <difficult>0</difficult>
    <bndbox>
        <xmin>837</xmin>
        <ymin>1698</ymin>
        <xmax>990</xmax>
        <ymax>1851</ymax>
    </bndbox>
    <name>IMAGE</name>
</object>
<object>
    <difficult>0</difficult>
    <bndbox>
        <xmin>1031</xmin>
        <ymin>1698</ymin>
        <xmax>1184</xmax>
        <ymax>1851</ymax>
    </bndbox>
    <name>IMAGE</name>
</object>
<object>
    <difficult>0</difficult>
    <bndbox>
        <xmin>663</xmin>
        <ymin>1574</ymin>
        <xmax>776</xmax>
        <ymax>1653</ymax>
    </bndbox>
    <name>TEXT</name>
</object>
<object>
    <difficult>0</difficult>
    <bndbox>
        <xmin>479</xmin>
        <ymin>2036</ymin>
        <xmax>961</xmax>
        <ymax>2234</ymax>
    </bndbox>
    <name>BUTTON</name>
</object>
</annotation>