<annotation><folder /><filename>C:\Users\rober_abgp8xd\Desktop\canada-trabajo\RICO_CLAY_data\unique_uis.tar\unique_uis\combined\29448.jpg</filename>
<path>C:\Users\rober_abgp8xd\Desktop\canada-trabajo\RICO_CLAY_data\unique_uis.tar\unique_uis\combined\29448.jpg</path>
<source><database>RICO</database></source><size><width>360</width><height>640</height><depth>3</depth></size><segmented>0</segmented><object>
    <difficult>0</difficult>
    <bndbox>
        <xmin>0</xmin>
        <ymin>84</ymin>
        <xmax>1440</xmax>
        <ymax>259</ymax>
    </bndbox>
    <name>CONTAINER</name>
</object>
<object>
    <difficult>0</difficult>
    <bndbox>
        <xmin>0</xmin>
        <ymin>84</ymin>
        <xmax>175</xmax>
        <ymax>259</ymax>
    </bndbox>
    <name>PICTOGRAM</name>
</object>
<object>
    <difficult>0</difficult>
    <bndbox>
        <xmin>1131</xmin>
        <ymin>131</ymin>
        <xmax>1422</xmax>
        <ymax>212</ymax>
    </bndbox>
    <name>BUTTON</name>
</object>
<object>
    <difficult>0</difficult>
    <bndbox>
        <xmin>349</xmin>
        <ymin>452</ymin>
        <xmax>1091</xmax>
        <ymax>554</ymax>
    </bndbox>
    <name>TEXT</name>
</object>
<object>
    <difficult>0</difficult>
    <bndbox>
        <xmin>552</xmin>
        <ymin>572</ymin>
        <xmax>888</xmax>
        <ymax>816</ymax>
    </bndbox>
    <name>PICTOGRAM</name>
</object>
<object>
    <difficult>0</difficult>
    <bndbox>
        <xmin>0</xmin>
        <ymin>572</ymin>
        <xmax>203</xmax>
        <ymax>740</ymax>
    </bndbox>
    <name>PICTOGRAM</name>
</object>
<object>
    <difficult>0</difficult>
    <bndbox>
        <xmin>0</xmin>
        <ymin>740</ymin>
        <xmax>1440</xmax>
        <ymax>2392</ymax>
    </bndbox>
    <name>CONTAINER</name>
</object>
<object>
    <difficult>0</difficult>
    <bndbox>
        <xmin>394</xmin>
        <ymin>1283</ymin>
        <xmax>1045</xmax>
        <ymax>1514</ymax>
    </bndbox>
    <name>TEXT</name>
</object>
<object>
    <difficult>0</difficult>
    <bndbox>
        <xmin>11</xmin>
        <ymin>2069</ymin>
        <xmax>1429</xmax>
        <ymax>2381</ymax>
    </bndbox>
    <name>CONTAINER</name>
</object>
<object>
    <difficult>0</difficult>
    <bndbox>
        <xmin>11</xmin>
        <ymin>2118</ymin>
        <xmax>484</xmax>
        <ymax>2381</ymax>
    </bndbox>
    <name>BUTTON</name>
</object>
<object>
    <difficult>0</difficult>
    <bndbox>
        <xmin>484</xmin>
        <ymin>2069</ymin>
        <xmax>957</xmax>
        <ymax>2381</ymax>
    </bndbox>
    <name>BUTTON</name>
</object>
<object>
    <difficult>0</difficult>
    <bndbox>
        <xmin>957</xmin>
        <ymin>2118</ymin>
        <xmax>1429</xmax>
        <ymax>2381</ymax>
    </bndbox>
    <name>BUTTON</name>
</object>
</annotation>