<annotation><folder /><filename>C:\Users\rober_abgp8xd\Desktop\canada-trabajo\RICO_CLAY_data\unique_uis.tar\unique_uis\combined\58158.jpg</filename>
<path>C:\Users\rober_abgp8xd\Desktop\canada-trabajo\RICO_CLAY_data\unique_uis.tar\unique_uis\combined\58158.jpg</path>
<source><database>RICO</database></source><size><width>360</width><height>640</height><depth>3</depth></size><segmented>0</segmented><object>
    <difficult>0</difficult>
    <bndbox>
        <xmin>56</xmin>
        <ymin>84</ymin>
        <xmax>1384</xmax>
        <ymax>2392</ymax>
    </bndbox>
    <name>CONTAINER</name>
</object>
<object>
    <difficult>0</difficult>
    <bndbox>
        <xmin>56</xmin>
        <ymin>84</ymin>
        <xmax>1384</xmax>
        <ymax>287</ymax>
    </bndbox>
    <name>TEXT</name>
</object>
<object>
    <difficult>0</difficult>
    <bndbox>
        <xmin>56</xmin>
        <ymin>287</ymin>
        <xmax>1384</xmax>
        <ymax>455</ymax>
    </bndbox>
    <name>CONTAINER</name>
</object>
<object>
    <difficult>0</difficult>
    <bndbox>
        <xmin>56</xmin>
        <ymin>315</ymin>
        <xmax>168</xmax>
        <ymax>427</ymax>
    </bndbox>
    <name>PICTOGRAM</name>
</object>
<object>
    <difficult>0</difficult>
    <bndbox>
        <xmin>224</xmin>
        <ymin>287</ymin>
        <xmax>1384</xmax>
        <ymax>455</ymax>
    </bndbox>
    <name>TEXT</name>
</object>
<object>
    <difficult>0</difficult>
    <bndbox>
        <xmin>56</xmin>
        <ymin>455</ymin>
        <xmax>1384</xmax>
        <ymax>623</ymax>
    </bndbox>
    <name>CONTAINER</name>
</object>
<object>
    <difficult>0</difficult>
    <bndbox>
        <xmin>56</xmin>
        <ymin>483</ymin>
        <xmax>168</xmax>
        <ymax>595</ymax>
    </bndbox>
    <name>PICTOGRAM</name>
</object>
<object>
    <difficult>0</difficult>
    <bndbox>
        <xmin>224</xmin>
        <ymin>455</ymin>
        <xmax>1384</xmax>
        <ymax>623</ymax>
    </bndbox>
    <name>TEXT</name>
</object>
<object>
    <difficult>0</difficult>
    <bndbox>
        <xmin>56</xmin>
        <ymin>623</ymin>
        <xmax>1384</xmax>
        <ymax>791</ymax>
    </bndbox>
    <name>CONTAINER</name>
</object>
<object>
    <difficult>0</difficult>
    <bndbox>
        <xmin>56</xmin>
        <ymin>651</ymin>
        <xmax>168</xmax>
        <ymax>763</ymax>
    </bndbox>
    <name>PICTOGRAM</name>
</object>
<object>
    <difficult>0</difficult>
    <bndbox>
        <xmin>224</xmin>
        <ymin>623</ymin>
        <xmax>1384</xmax>
        <ymax>791</ymax>
    </bndbox>
    <name>TEXT</name>
</object>
<object>
    <difficult>0</difficult>
    <bndbox>
        <xmin>56</xmin>
        <ymin>791</ymin>
        <xmax>1384</xmax>
        <ymax>959</ymax>
    </bndbox>
    <name>CONTAINER</name>
</object>
<object>
    <difficult>0</difficult>
    <bndbox>
        <xmin>56</xmin>
        <ymin>819</ymin>
        <xmax>168</xmax>
        <ymax>931</ymax>
    </bndbox>
    <name>PICTOGRAM</name>
</object>
<object>
    <difficult>0</difficult>
    <bndbox>
        <xmin>224</xmin>
        <ymin>791</ymin>
        <xmax>1384</xmax>
        <ymax>959</ymax>
    </bndbox>
    <name>TEXT</name>
</object>
<object>
    <difficult>0</difficult>
    <bndbox>
        <xmin>56</xmin>
        <ymin>959</ymin>
        <xmax>1384</xmax>
        <ymax>1127</ymax>
    </bndbox>
    <name>CONTAINER</name>
</object>
<object>
    <difficult>0</difficult>
    <bndbox>
        <xmin>56</xmin>
        <ymin>987</ymin>
        <xmax>168</xmax>
        <ymax>1099</ymax>
    </bndbox>
    <name>PICTOGRAM</name>
</object>
<object>
    <difficult>0</difficult>
    <bndbox>
        <xmin>224</xmin>
        <ymin>959</ymin>
        <xmax>1384</xmax>
        <ymax>1127</ymax>
    </bndbox>
    <name>TEXT</name>
</object>
<object>
    <difficult>0</difficult>
    <bndbox>
        <xmin>56</xmin>
        <ymin>1127</ymin>
        <xmax>1384</xmax>
        <ymax>1295</ymax>
    </bndbox>
    <name>CONTAINER</name>
</object>
<object>
    <difficult>0</difficult>
    <bndbox>
        <xmin>56</xmin>
        <ymin>1155</ymin>
        <xmax>168</xmax>
        <ymax>1267</ymax>
    </bndbox>
    <name>PICTOGRAM</name>
</object>
<object>
    <difficult>0</difficult>
    <bndbox>
        <xmin>224</xmin>
        <ymin>1127</ymin>
        <xmax>1384</xmax>
        <ymax>1295</ymax>
    </bndbox>
    <name>TEXT</name>
</object>
<object>
    <difficult>0</difficult>
    <bndbox>
        <xmin>56</xmin>
        <ymin>1295</ymin>
        <xmax>1384</xmax>
        <ymax>1463</ymax>
    </bndbox>
    <name>CONTAINER</name>
</object>
<object>
    <difficult>0</difficult>
    <bndbox>
        <xmin>56</xmin>
        <ymin>1323</ymin>
        <xmax>168</xmax>
        <ymax>1435</ymax>
    </bndbox>
    <name>PICTOGRAM</name>
</object>
<object>
    <difficult>0</difficult>
    <bndbox>
        <xmin>224</xmin>
        <ymin>1295</ymin>
        <xmax>1384</xmax>
        <ymax>1463</ymax>
    </bndbox>
    <name>TEXT</name>
</object>
</annotation>