<annotation><folder /><filename>C:\Users\rober_abgp8xd\Desktop\canada-trabajo\RICO_CLAY_data\unique_uis.tar\unique_uis\combined\70478.jpg</filename>
<path>C:\Users\rober_abgp8xd\Desktop\canada-trabajo\RICO_CLAY_data\unique_uis.tar\unique_uis\combined\70478.jpg</path>
<source><database>RICO</database></source><size><width>360</width><height>640</height><depth>3</depth></size><segmented>0</segmented><object>
    <difficult>0</difficult>
    <bndbox>
        <xmin>0</xmin>
        <ymin>84</ymin>
        <xmax>1440</xmax>
        <ymax>280</ymax>
    </bndbox>
    <name>BACKGROUND</name>
</object>
<object>
    <difficult>0</difficult>
    <bndbox>
        <xmin>1300</xmin>
        <ymin>98</ymin>
        <xmax>1440</xmax>
        <ymax>266</ymax>
    </bndbox>
    <name>BACKGROUND</name>
</object>
<object>
    <difficult>0</difficult>
    <bndbox>
        <xmin>0</xmin>
        <ymin>280</ymin>
        <xmax>1440</xmax>
        <ymax>1870</ymax>
    </bndbox>
    <name>BACKGROUND</name>
</object>
<object>
    <difficult>0</difficult>
    <bndbox>
        <xmin>0</xmin>
        <ymin>508</ymin>
        <xmax>1440</xmax>
        <ymax>704</ymax>
    </bndbox>
    <name>BACKGROUND</name>
</object>
<object>
    <difficult>0</difficult>
    <bndbox>
        <xmin>0</xmin>
        <ymin>704</ymin>
        <xmax>1440</xmax>
        <ymax>872</ymax>
    </bndbox>
    <name>BACKGROUND</name>
</object>
<object>
    <difficult>0</difficult>
    <bndbox>
        <xmin>0</xmin>
        <ymin>872</ymin>
        <xmax>1440</xmax>
        <ymax>1068</ymax>
    </bndbox>
    <name>BACKGROUND</name>
</object>
<object>
    <difficult>0</difficult>
    <bndbox>
        <xmin>0</xmin>
        <ymin>1072</ymin>
        <xmax>1440</xmax>
        <ymax>1268</ymax>
    </bndbox>
    <name>BACKGROUND</name>
</object>
<object>
    <difficult>0</difficult>
    <bndbox>
        <xmin>0</xmin>
        <ymin>1272</ymin>
        <xmax>1440</xmax>
        <ymax>1468</ymax>
    </bndbox>
    <name>BACKGROUND</name>
</object>
<object>
    <difficult>0</difficult>
    <bndbox>
        <xmin>0</xmin>
        <ymin>1524</ymin>
        <xmax>1440</xmax>
        <ymax>1590</ymax>
    </bndbox>
    <name>BACKGROUND</name>
</object>
<object>
    <difficult>0</difficult>
    <bndbox>
        <xmin>0</xmin>
        <ymin>0</ymin>
        <xmax>1176</xmax>
        <ymax>2392</ymax>
    </bndbox>
    <name>DRAWER</name>
</object>
<object>
    <difficult>0</difficult>
    <bndbox>
        <xmin>0</xmin>
        <ymin>0</ymin>
        <xmax>1176</xmax>
        <ymax>661</ymax>
    </bndbox>
    <name>CONTAINER</name>
</object>
<object>
    <difficult>0</difficult>
    <bndbox>
        <xmin>56</xmin>
        <ymin>437</ymin>
        <xmax>1176</xmax>
        <ymax>633</ymax>
    </bndbox>
    <name>CONTAINER</name>
</object>
<object>
    <difficult>0</difficult>
    <bndbox>
        <xmin>56</xmin>
        <ymin>469</ymin>
        <xmax>323</xmax>
        <ymax>535</ymax>
    </bndbox>
    <name>TEXT</name>
</object>
<object>
    <difficult>0</difficult>
    <bndbox>
        <xmin>56</xmin>
        <ymin>535</ymin>
        <xmax>601</xmax>
        <ymax>601</ymax>
    </bndbox>
    <name>TEXT</name>
</object>
<object>
    <difficult>0</difficult>
    <bndbox>
        <xmin>56</xmin>
        <ymin>202</ymin>
        <xmax>280</xmax>
        <ymax>426</ymax>
    </bndbox>
    <name>PICTOGRAM</name>
</object>
<object>
    <difficult>0</difficult>
    <bndbox>
        <xmin>0</xmin>
        <ymin>661</ymin>
        <xmax>1176</xmax>
        <ymax>2168</ymax>
    </bndbox>
    <name>CONTAINER</name>
</object>
<object>
    <difficult>0</difficult>
    <bndbox>
        <xmin>0</xmin>
        <ymin>689</ymin>
        <xmax>1176</xmax>
        <ymax>857</ymax>
    </bndbox>
    <name>CONTAINER</name>
</object>
<object>
    <difficult>0</difficult>
    <bndbox>
        <xmin>56</xmin>
        <ymin>727</ymin>
        <xmax>147</xmax>
        <ymax>818</ymax>
    </bndbox>
    <name>PICTOGRAM</name>
</object>
<object>
    <difficult>0</difficult>
    <bndbox>
        <xmin>252</xmin>
        <ymin>740</ymin>
        <xmax>490</xmax>
        <ymax>806</ymax>
    </bndbox>
    <name>TEXT</name>
</object>
<object>
    <difficult>0</difficult>
    <bndbox>
        <xmin>0</xmin>
        <ymin>857</ymin>
        <xmax>1176</xmax>
        <ymax>1025</ymax>
    </bndbox>
    <name>CONTAINER</name>
</object>
<object>
    <difficult>0</difficult>
    <bndbox>
        <xmin>56</xmin>
        <ymin>895</ymin>
        <xmax>147</xmax>
        <ymax>986</ymax>
    </bndbox>
    <name>PICTOGRAM</name>
</object>
<object>
    <difficult>0</difficult>
    <bndbox>
        <xmin>252</xmin>
        <ymin>908</ymin>
        <xmax>448</xmax>
        <ymax>974</ymax>
    </bndbox>
    <name>TEXT</name>
</object>
<object>
    <difficult>0</difficult>
    <bndbox>
        <xmin>0</xmin>
        <ymin>1025</ymin>
        <xmax>1176</xmax>
        <ymax>1193</ymax>
    </bndbox>
    <name>CONTAINER</name>
</object>
<object>
    <difficult>0</difficult>
    <bndbox>
        <xmin>56</xmin>
        <ymin>1063</ymin>
        <xmax>147</xmax>
        <ymax>1154</ymax>
    </bndbox>
    <name>PICTOGRAM</name>
</object>
<object>
    <difficult>0</difficult>
    <bndbox>
        <xmin>252</xmin>
        <ymin>1076</ymin>
        <xmax>380</xmax>
        <ymax>1142</ymax>
    </bndbox>
    <name>TEXT</name>
</object>
<object>
    <difficult>0</difficult>
    <bndbox>
        <xmin>0</xmin>
        <ymin>1193</ymin>
        <xmax>1176</xmax>
        <ymax>1361</ymax>
    </bndbox>
    <name>CONTAINER</name>
</object>
<object>
    <difficult>0</difficult>
    <bndbox>
        <xmin>56</xmin>
        <ymin>1231</ymin>
        <xmax>147</xmax>
        <ymax>1322</ymax>
    </bndbox>
    <name>PICTOGRAM</name>
</object>
<object>
    <difficult>0</difficult>
    <bndbox>
        <xmin>252</xmin>
        <ymin>1244</ymin>
        <xmax>399</xmax>
        <ymax>1310</ymax>
    </bndbox>
    <name>TEXT</name>
</object>
<object>
    <difficult>0</difficult>
    <bndbox>
        <xmin>0</xmin>
        <ymin>1361</ymin>
        <xmax>1176</xmax>
        <ymax>1529</ymax>
    </bndbox>
    <name>CONTAINER</name>
</object>
<object>
    <difficult>0</difficult>
    <bndbox>
        <xmin>56</xmin>
        <ymin>1399</ymin>
        <xmax>147</xmax>
        <ymax>1490</ymax>
    </bndbox>
    <name>PICTOGRAM</name>
</object>
<object>
    <difficult>0</difficult>
    <bndbox>
        <xmin>252</xmin>
        <ymin>1412</ymin>
        <xmax>453</xmax>
        <ymax>1478</ymax>
    </bndbox>
    <name>TEXT</name>
</object>
<object>
    <difficult>0</difficult>
    <bndbox>
        <xmin>0</xmin>
        <ymin>1529</ymin>
        <xmax>1176</xmax>
        <ymax>1697</ymax>
    </bndbox>
    <name>CONTAINER</name>
</object>
<object>
    <difficult>0</difficult>
    <bndbox>
        <xmin>56</xmin>
        <ymin>1567</ymin>
        <xmax>147</xmax>
        <ymax>1658</ymax>
    </bndbox>
    <name>PICTOGRAM</name>
</object>
<object>
    <difficult>0</difficult>
    <bndbox>
        <xmin>252</xmin>
        <ymin>1580</ymin>
        <xmax>433</xmax>
        <ymax>1646</ymax>
    </bndbox>
    <name>TEXT</name>
</object>
<object>
    <difficult>0</difficult>
    <bndbox>
        <xmin>56</xmin>
        <ymin>2247</ymin>
        <xmax>651</xmax>
        <ymax>2313</ymax>
    </bndbox>
    <name>TEXT</name>
</object>
</annotation>