{
  "activity_name": "com.yandex.browser/com.yandex.browser.YandexBrowserMainActivity", 
  "activity": {
    "root": {
      "scrollable-horizontal": false, 
      "draw": true, 
      "ancestors": [
        "android.widget.FrameLayout", 
        "android.view.ViewGroup", 
        "android.view.View", 
        "java.lang.Object"
      ], 
      "clickable": false, 
      "pressed": "not_pressed", 
      "focusable": false, 
      "long-clickable": false, 
      "enabled": true, 
      "bounds": [
        339, 
        662, 
        1412, 
        1839
      ], 
      "visibility": "visible", 
      "content-desc": [
        null
      ], 
      "rel-bounds": [
        0, 
        0, 
        1073, 
        1177
      ], 
      "focused": false, 
      "selected": false, 
      "scrollable-vertical": false, 
      "children": [
        {
          "resource-id": "com.yandex.browser:id/bro_custo_menu", 
          "adapter-view": false, 
          "pointer": "d364d86", 
          "children": [
            {
              "resource-id": "com.yandex.browser:id/bro_custo_menu_inner", 
              "adapter-view": false, 
              "pointer": "7620647", 
              "children": [
                {
                  "resource-id": "com.yandex.browser:id/bro_custo_menu_regular", 
                  "adapter-view": false, 
                  "pointer": "4907e74", 
                  "children": [
                    {
                      "resource-id": "com.yandex.browser:id/bro_menu_item_new_incognito_tab", 
                      "adapter-view": false, 
                      "pointer": "9c55f9d", 
                      "children": [
                        {
                          "text": "New Incognito tab", 
                          "resource-id": "com.yandex.browser:id/menu_item_text_view", 
                          "adapter-view": false, 
                          "pointer": "c99bc12", 
                          "scrollable-horizontal": false, 
                          "ancestors": [
                            "android.widget.TextView", 
                            "android.view.View", 
                            "java.lang.Object"
                          ], 
                          "selected": false, 
                          "content-desc": [
                            null
                          ], 
                          "rel-bounds": [
                            0, 
                            0, 
                            703, 
                            168
                          ], 
                          "draw": false, 
                          "focusable": false, 
                          "long-clickable": false, 
                          "visibility": "visible", 
                          "focused": false, 
                          "clickable": false, 
                          "abs-pos": true, 
                          "font-family": "sans-serif", 
                          "class": "ia", 
                          "visible-to-user": true, 
                          "package": "com.yandex.browser", 
                          "enabled": true, 
                          "bounds": [
                            395, 
                            747, 
                            1098, 
                            915
                          ], 
                          "pressed": "not_pressed", 
                          "scrollable-vertical": false
                        }, 
                        {
                          "resource-id": "com.yandex.browser:id/menu_item_highlight_dot_image_view", 
                          "adapter-view": false, 
                          "pointer": "caebfe3", 
                          "scrollable-horizontal": false, 
                          "ancestors": [
                            "android.widget.ImageView", 
                            "android.view.View", 
                            "java.lang.Object"
                          ], 
                          "selected": false, 
                          "content-desc": [
                            null
                          ], 
                          "rel-bounds": [
                            0, 
                            0, 
                            0, 
                            0
                          ], 
                          "draw": false, 
                          "focusable": false, 
                          "long-clickable": false, 
                          "visibility": "gone", 
                          "focused": false, 
                          "clickable": false, 
                          "abs-pos": true, 
                          "class": "hp", 
                          "visible-to-user": false, 
                          "package": "com.yandex.browser", 
                          "enabled": true, 
                          "bounds": [
                            395, 
                            747, 
                            395, 
                            747
                          ], 
                          "pressed": "not_pressed", 
                          "scrollable-vertical": false
                        }
                      ], 
                      "scrollable-horizontal": false, 
                      "ancestors": [
                        "android.view.ViewGroup", 
                        "android.view.View", 
                        "java.lang.Object"
                      ], 
                      "selected": false, 
                      "content-desc": [
                        null
                      ], 
                      "rel-bounds": [
                        0, 
                        0, 
                        960, 
                        168
                      ], 
                      "draw": true, 
                      "focusable": false, 
                      "long-clickable": false, 
                      "visibility": "visible", 
                      "focused": false, 
                      "clickable": true, 
                      "abs-pos": true, 
                      "class": "android.widget.LinearLayout", 
                      "visible-to-user": true, 
                      "package": "com.yandex.browser", 
                      "enabled": true, 
                      "bounds": [
                        395, 
                        747, 
                        1355, 
                        915
                      ], 
                      "pressed": "not_pressed", 
                      "scrollable-vertical": false
                    }, 
                    {
                      "resource-id": "com.yandex.browser:id/bro_menu_item_change_background", 
                      "adapter-view": false, 
                      "pointer": "1710de0", 
                      "children": [
                        {
                          "text": "Change background", 
                          "resource-id": "com.yandex.browser:id/menu_item_text_view", 
                          "adapter-view": false, 
                          "pointer": "a9d5899", 
                          "scrollable-horizontal": false, 
                          "ancestors": [
                            "android.widget.TextView", 
                            "android.view.View", 
                            "java.lang.Object"
                          ], 
                          "selected": false, 
                          "content-desc": [
                            null
                          ], 
                          "rel-bounds": [
                            0, 
                            0, 
                            747, 
                            168
                          ], 
                          "draw": false, 
                          "focusable": false, 
                          "long-clickable": false, 
                          "visibility": "visible", 
                          "focused": false, 
                          "clickable": false, 
                          "abs-pos": true, 
                          "font-family": "sans-serif", 
                          "class": "ia", 
                          "visible-to-user": true, 
                          "package": "com.yandex.browser", 
                          "enabled": true, 
                          "bounds": [
                            395, 
                            915, 
                            1142, 
                            1083
                          ], 
                          "pressed": "not_pressed", 
                          "scrollable-vertical": false
                        }, 
                        {
                          "resource-id": "com.yandex.browser:id/menu_item_highlight_dot_image_view", 
                          "adapter-view": false, 
                          "pointer": "553875e", 
                          "scrollable-horizontal": false, 
                          "ancestors": [
                            "android.widget.ImageView", 
                            "android.view.View", 
                            "java.lang.Object"
                          ], 
                          "selected": false, 
                          "content-desc": [
                            null
                          ], 
                          "rel-bounds": [
                            0, 
                            0, 
                            0, 
                            0
                          ], 
                          "draw": false, 
                          "focusable": false, 
                          "long-clickable": false, 
                          "visibility": "gone", 
                          "focused": false, 
                          "clickable": false, 
                          "abs-pos": true, 
                          "class": "hp", 
                          "visible-to-user": false, 
                          "package": "com.yandex.browser", 
                          "enabled": true, 
                          "bounds": [
                            395, 
                            915, 
                            395, 
                            915
                          ], 
                          "pressed": "not_pressed", 
                          "scrollable-vertical": false
                        }
                      ], 
                      "scrollable-horizontal": false, 
                      "ancestors": [
                        "android.view.ViewGroup", 
                        "android.view.View", 
                        "java.lang.Object"
                      ], 
                      "selected": false, 
                      "content-desc": [
                        null
                      ], 
                      "rel-bounds": [
                        0, 
                        168, 
                        960, 
                        336
                      ], 
                      "draw": true, 
                      "focusable": false, 
                      "long-clickable": false, 
                      "visibility": "visible", 
                      "focused": false, 
                      "clickable": true, 
                      "abs-pos": true, 
                      "class": "android.widget.LinearLayout", 
                      "visible-to-user": true, 
                      "package": "com.yandex.browser", 
                      "enabled": true, 
                      "bounds": [
                        395, 
                        915, 
                        1355, 
                        1083
                      ], 
                      "pressed": "not_pressed", 
                      "scrollable-vertical": false
                    }, 
                    {
                      "resource-id": "com.yandex.browser:id/bro_menu_item_zen_settings", 
                      "adapter-view": false, 
                      "pointer": "883773f", 
                      "children": [
                        {
                          "text": "Configure recommendations", 
                          "resource-id": "com.yandex.browser:id/menu_item_text_view", 
                          "adapter-view": false, 
                          "pointer": "809280c", 
                          "scrollable-horizontal": false, 
                          "ancestors": [
                            "android.widget.TextView", 
                            "android.view.View", 
                            "java.lang.Object"
                          ], 
                          "selected": false, 
                          "content-desc": [
                            null
                          ], 
                          "rel-bounds": [
                            0, 
                            0, 
                            960, 
                            168
                          ], 
                          "draw": false, 
                          "focusable": false, 
                          "long-clickable": false, 
                          "visibility": "visible", 
                          "focused": false, 
                          "clickable": false, 
                          "abs-pos": true, 
                          "font-family": "sans-serif", 
                          "class": "ia", 
                          "visible-to-user": true, 
                          "package": "com.yandex.browser", 
                          "enabled": true, 
                          "bounds": [
                            395, 
                            1083, 
                            1355, 
                            1251
                          ], 
                          "pressed": "not_pressed", 
                          "scrollable-vertical": false
                        }, 
                        {
                          "resource-id": "com.yandex.browser:id/menu_item_highlight_dot_image_view", 
                          "adapter-view": false, 
                          "pointer": "b61e555", 
                          "scrollable-horizontal": false, 
                          "ancestors": [
                            "android.widget.ImageView", 
                            "android.view.View", 
                            "java.lang.Object"
                          ], 
                          "selected": false, 
                          "content-desc": [
                            null
                          ], 
                          "rel-bounds": [
                            0, 
                            0, 
                            0, 
                            0
                          ], 
                          "draw": false, 
                          "focusable": false, 
                          "long-clickable": false, 
                          "visibility": "gone", 
                          "focused": false, 
                          "clickable": false, 
                          "abs-pos": true, 
                          "class": "hp", 
                          "visible-to-user": false, 
                          "package": "com.yandex.browser", 
                          "enabled": true, 
                          "bounds": [
                            395, 
                            1083, 
                            395, 
                            1083
                          ], 
                          "pressed": "not_pressed", 
                          "scrollable-vertical": false
                        }
                      ], 
                      "scrollable-horizontal": false, 
                      "ancestors": [
                        "android.view.ViewGroup", 
                        "android.view.View", 
                        "java.lang.Object"
                      ], 
                      "selected": false, 
                      "content-desc": [
                        null
                      ], 
                      "rel-bounds": [
                        0, 
                        336, 
                        960, 
                        504
                      ], 
                      "draw": true, 
                      "focusable": false, 
                      "long-clickable": false, 
                      "visibility": "visible", 
                      "focused": false, 
                      "clickable": true, 
                      "abs-pos": true, 
                      "class": "android.widget.LinearLayout", 
                      "visible-to-user": true, 
                      "package": "com.yandex.browser", 
                      "enabled": true, 
                      "bounds": [
                        395, 
                        1083, 
                        1355, 
                        1251
                      ], 
                      "pressed": "not_pressed", 
                      "scrollable-vertical": false
                    }, 
                    {
                      "resource-id": "com.yandex.browser:id/bro_menu_item_set_default", 
                      "adapter-view": false, 
                      "pointer": "14cbb6a", 
                      "children": [
                        {
                          "text": "Set as default browser", 
                          "resource-id": "com.yandex.browser:id/menu_item_text_view", 
                          "adapter-view": false, 
                          "pointer": "cc2485b", 
                          "scrollable-horizontal": false, 
                          "ancestors": [
                            "android.widget.TextView", 
                            "android.view.View", 
                            "java.lang.Object"
                          ], 
                          "selected": false, 
                          "content-desc": [
                            null
                          ], 
                          "rel-bounds": [
                            0, 
                            0, 
                            809, 
                            168
                          ], 
                          "draw": false, 
                          "focusable": false, 
                          "long-clickable": false, 
                          "visibility": "visible", 
                          "focused": false, 
                          "clickable": false, 
                          "abs-pos": true, 
                          "font-family": "sans-serif", 
                          "class": "ia", 
                          "visible-to-user": true, 
                          "package": "com.yandex.browser", 
                          "enabled": true, 
                          "bounds": [
                            395, 
                            1251, 
                            1204, 
                            1419
                          ], 
                          "pressed": "not_pressed", 
                          "scrollable-vertical": false
                        }, 
                        {
                          "resource-id": "com.yandex.browser:id/menu_item_highlight_dot_image_view", 
                          "adapter-view": false, 
                          "pointer": "226b8f8", 
                          "scrollable-horizontal": false, 
                          "ancestors": [
                            "android.widget.ImageView", 
                            "android.view.View", 
                            "java.lang.Object"
                          ], 
                          "selected": false, 
                          "content-desc": [
                            null
                          ], 
                          "rel-bounds": [
                            0, 
                            0, 
                            0, 
                            0
                          ], 
                          "draw": false, 
                          "focusable": false, 
                          "long-clickable": false, 
                          "visibility": "gone", 
                          "focused": false, 
                          "clickable": false, 
                          "abs-pos": true, 
                          "class": "hp", 
                          "visible-to-user": false, 
                          "package": "com.yandex.browser", 
                          "enabled": true, 
                          "bounds": [
                            395, 
                            1251, 
                            395, 
                            1251
                          ], 
                          "pressed": "not_pressed", 
                          "scrollable-vertical": false
                        }
                      ], 
                      "scrollable-horizontal": false, 
                      "ancestors": [
                        "android.view.ViewGroup", 
                        "android.view.View", 
                        "java.lang.Object"
                      ], 
                      "selected": false, 
                      "content-desc": [
                        null
                      ], 
                      "rel-bounds": [
                        0, 
                        504, 
                        960, 
                        672
                      ], 
                      "draw": true, 
                      "focusable": false, 
                      "long-clickable": false, 
                      "visibility": "visible", 
                      "focused": false, 
                      "clickable": true, 
                      "abs-pos": true, 
                      "class": "android.widget.LinearLayout", 
                      "visible-to-user": true, 
                      "package": "com.yandex.browser", 
                      "enabled": true, 
                      "bounds": [
                        395, 
                        1251, 
                        1355, 
                        1419
                      ], 
                      "pressed": "not_pressed", 
                      "scrollable-vertical": false
                    }, 
                    {
                      "resource-id": "com.yandex.browser:id/bro_menu_item_settings", 
                      "adapter-view": false, 
                      "pointer": "ea881d1", 
                      "children": [
                        {
                          "text": "Settings", 
                          "resource-id": "com.yandex.browser:id/menu_item_text_view", 
                          "adapter-view": false, 
                          "pointer": "df32436", 
                          "scrollable-horizontal": false, 
                          "ancestors": [
                            "android.widget.TextView", 
                            "android.view.View", 
                            "java.lang.Object"
                          ], 
                          "selected": false, 
                          "content-desc": [
                            null
                          ], 
                          "rel-bounds": [
                            0, 
                            0, 
                            456, 
                            168
                          ], 
                          "draw": false, 
                          "focusable": false, 
                          "long-clickable": false, 
                          "visibility": "visible", 
                          "focused": false, 
                          "clickable": false, 
                          "abs-pos": true, 
                          "font-family": "sans-serif", 
                          "class": "ia", 
                          "visible-to-user": true, 
                          "package": "com.yandex.browser", 
                          "enabled": true, 
                          "bounds": [
                            395, 
                            1419, 
                            851, 
                            1587
                          ], 
                          "pressed": "not_pressed", 
                          "scrollable-vertical": false
                        }, 
                        {
                          "resource-id": "com.yandex.browser:id/menu_item_highlight_dot_image_view", 
                          "adapter-view": false, 
                          "pointer": "d530f37", 
                          "scrollable-horizontal": false, 
                          "ancestors": [
                            "android.widget.ImageView", 
                            "android.view.View", 
                            "java.lang.Object"
                          ], 
                          "selected": false, 
                          "content-desc": [
                            null
                          ], 
                          "rel-bounds": [
                            0, 
                            0, 
                            0, 
                            0
                          ], 
                          "draw": false, 
                          "focusable": false, 
                          "long-clickable": false, 
                          "visibility": "gone", 
                          "focused": false, 
                          "clickable": false, 
                          "abs-pos": true, 
                          "class": "hp", 
                          "visible-to-user": false, 
                          "package": "com.yandex.browser", 
                          "enabled": true, 
                          "bounds": [
                            395, 
                            1419, 
                            395, 
                            1419
                          ], 
                          "pressed": "not_pressed", 
                          "scrollable-vertical": false
                        }
                      ], 
                      "scrollable-horizontal": false, 
                      "ancestors": [
                        "android.view.ViewGroup", 
                        "android.view.View", 
                        "java.lang.Object"
                      ], 
                      "selected": false, 
                      "content-desc": [
                        null
                      ], 
                      "rel-bounds": [
                        0, 
                        672, 
                        960, 
                        840
                      ], 
                      "draw": true, 
                      "focusable": false, 
                      "long-clickable": false, 
                      "visibility": "visible", 
                      "focused": false, 
                      "clickable": true, 
                      "abs-pos": true, 
                      "class": "android.widget.LinearLayout", 
                      "visible-to-user": true, 
                      "package": "com.yandex.browser", 
                      "enabled": true, 
                      "bounds": [
                        395, 
                        1419, 
                        1355, 
                        1587
                      ], 
                      "pressed": "not_pressed", 
                      "scrollable-vertical": false
                    }, 
                    {
                      "resource-id": "com.yandex.browser:id/bro_menu_item_exit", 
                      "adapter-view": false, 
                      "pointer": "68a6ca4", 
                      "children": [
                        {
                          "text": "Exit", 
                          "resource-id": "com.yandex.browser:id/menu_item_text_view", 
                          "adapter-view": false, 
                          "pointer": "e26a0d", 
                          "scrollable-horizontal": false, 
                          "ancestors": [
                            "android.widget.TextView", 
                            "android.view.View", 
                            "java.lang.Object"
                          ], 
                          "selected": false, 
                          "content-desc": [
                            null
                          ], 
                          "rel-bounds": [
                            0, 
                            0, 
                            344, 
                            168
                          ], 
                          "draw": false, 
                          "focusable": false, 
                          "long-clickable": false, 
                          "visibility": "visible", 
                          "focused": false, 
                          "clickable": false, 
                          "abs-pos": true, 
                          "font-family": "sans-serif", 
                          "class": "ia", 
                          "visible-to-user": true, 
                          "package": "com.yandex.browser", 
                          "enabled": true, 
                          "bounds": [
                            395, 
                            1587, 
                            739, 
                            1755
                          ], 
                          "pressed": "not_pressed", 
                          "scrollable-vertical": false
                        }, 
                        {
                          "resource-id": "com.yandex.browser:id/menu_item_highlight_dot_image_view", 
                          "adapter-view": false, 
                          "pointer": "fc54dc2", 
                          "scrollable-horizontal": false, 
                          "ancestors": [
                            "android.widget.ImageView", 
                            "android.view.View", 
                            "java.lang.Object"
                          ], 
                          "selected": false, 
                          "content-desc": [
                            null
                          ], 
                          "rel-bounds": [
                            0, 
                            0, 
                            0, 
                            0
                          ], 
                          "draw": false, 
                          "focusable": false, 
                          "long-clickable": false, 
                          "visibility": "gone", 
                          "focused": false, 
                          "clickable": false, 
                          "abs-pos": true, 
                          "class": "hp", 
                          "visible-to-user": false, 
                          "package": "com.yandex.browser", 
                          "enabled": true, 
                          "bounds": [
                            395, 
                            1587, 
                            395, 
                            1587
                          ], 
                          "pressed": "not_pressed", 
                          "scrollable-vertical": false
                        }
                      ], 
                      "scrollable-horizontal": false, 
                      "ancestors": [
                        "android.view.ViewGroup", 
                        "android.view.View", 
                        "java.lang.Object"
                      ], 
                      "selected": false, 
                      "content-desc": [
                        null
                      ], 
                      "rel-bounds": [
                        0, 
                        840, 
                        960, 
                        1008
                      ], 
                      "draw": true, 
                      "focusable": false, 
                      "long-clickable": false, 
                      "visibility": "visible", 
                      "focused": false, 
                      "clickable": true, 
                      "abs-pos": true, 
                      "class": "android.widget.LinearLayout", 
                      "visible-to-user": true, 
                      "package": "com.yandex.browser", 
                      "enabled": true, 
                      "bounds": [
                        395, 
                        1587, 
                        1355, 
                        1755
                      ], 
                      "pressed": "not_pressed", 
                      "scrollable-vertical": false
                    }
                  ], 
                  "scrollable-horizontal": false, 
                  "ancestors": [
                    "android.view.ViewGroup", 
                    "android.view.View", 
                    "java.lang.Object"
                  ], 
                  "selected": false, 
                  "content-desc": [
                    null
                  ], 
                  "rel-bounds": [
                    0, 
                    28, 
                    960, 
                    1036
                  ], 
                  "draw": true, 
                  "focusable": false, 
                  "long-clickable": false, 
                  "visibility": "visible", 
                  "focused": false, 
                  "clickable": false, 
                  "abs-pos": true, 
                  "class": "android.widget.LinearLayout", 
                  "visible-to-user": true, 
                  "package": "com.yandex.browser", 
                  "enabled": true, 
                  "bounds": [
                    395, 
                    747, 
                    1355, 
                    1755
                  ], 
                  "pressed": "not_pressed", 
                  "scrollable-vertical": false
                }, 
                {
                  "resource-id": "com.yandex.browser:id/bro_menu_basement_separator", 
                  "adapter-view": false, 
                  "pointer": "abf67d3", 
                  "scrollable-horizontal": false, 
                  "ancestors": [
                    "java.lang.Object"
                  ], 
                  "selected": false, 
                  "content-desc": [
                    null
                  ], 
                  "rel-bounds": [
                    0, 
                    0, 
                    0, 
                    0
                  ], 
                  "draw": false, 
                  "focusable": false, 
                  "long-clickable": false, 
                  "visibility": "gone", 
                  "focused": false, 
                  "clickable": false, 
                  "abs-pos": true, 
                  "class": "android.view.View", 
                  "visible-to-user": false, 
                  "package": "com.yandex.browser", 
                  "enabled": true, 
                  "bounds": [
                    395, 
                    719, 
                    395, 
                    719
                  ], 
                  "pressed": "not_pressed", 
                  "scrollable-vertical": false
                }, 
                {
                  "resource-id": "com.yandex.browser:id/bro_custo_menu_basement", 
                  "adapter-view": false, 
                  "pointer": "553af10", 
                  "scrollable-horizontal": false, 
                  "ancestors": [
                    "android.view.ViewGroup", 
                    "android.view.View", 
                    "java.lang.Object"
                  ], 
                  "selected": false, 
                  "content-desc": [
                    null
                  ], 
                  "rel-bounds": [
                    0, 
                    0, 
                    0, 
                    0
                  ], 
                  "draw": true, 
                  "focusable": false, 
                  "long-clickable": false, 
                  "visibility": "gone", 
                  "focused": false, 
                  "clickable": false, 
                  "abs-pos": true, 
                  "class": "android.widget.LinearLayout", 
                  "visible-to-user": false, 
                  "package": "com.yandex.browser", 
                  "enabled": true, 
                  "bounds": [
                    395, 
                    719, 
                    395, 
                    719
                  ], 
                  "pressed": "not_pressed", 
                  "scrollable-vertical": false
                }
              ], 
              "scrollable-horizontal": false, 
              "ancestors": [
                "android.widget.LinearLayout", 
                "android.view.ViewGroup", 
                "android.view.View", 
                "java.lang.Object"
              ], 
              "selected": false, 
              "content-desc": [
                null
              ], 
              "rel-bounds": [
                0, 
                0, 
                960, 
                1064
              ], 
              "draw": true, 
              "focusable": false, 
              "long-clickable": false, 
              "visibility": "visible", 
              "focused": false, 
              "clickable": false, 
              "abs-pos": true, 
              "class": "com.yandex.browser.menu.views.MenuContainerLayout", 
              "visible-to-user": true, 
              "package": "com.yandex.browser", 
              "enabled": true, 
              "bounds": [
                395, 
                719, 
                1355, 
                1783
              ], 
              "pressed": "not_pressed", 
              "scrollable-vertical": false
            }
          ], 
          "scrollable-horizontal": false, 
          "ancestors": [
            "android.widget.ScrollView", 
            "android.widget.FrameLayout", 
            "android.view.ViewGroup", 
            "android.view.View", 
            "java.lang.Object"
          ], 
          "selected": false, 
          "content-desc": [
            null
          ], 
          "rel-bounds": [
            56, 
            57, 
            1016, 
            1121
          ], 
          "draw": false, 
          "focusable": true, 
          "long-clickable": false, 
          "visibility": "visible", 
          "focused": false, 
          "clickable": false, 
          "abs-pos": true, 
          "class": "com.yandex.browser.menu.views.MenuScrollView", 
          "visible-to-user": true, 
          "package": "com.yandex.browser", 
          "enabled": true, 
          "bounds": [
            395, 
            719, 
            1355, 
            1783
          ], 
          "pressed": "not_pressed", 
          "scrollable-vertical": false
        }
      ], 
      "adapter-view": false, 
      "abs-pos": true, 
      "pointer": "5e43e61", 
      "class": "aze$e", 
      "visible-to-user": true
    }, 
    "added_fragments": [], 
    "active_fragments": []
  }, 
  "is_keyboard_deployed": false, 
  "request_id": "73"
}